<?xml version="1.0" encoding="UTF-8" standalone="yes"?>
<movies id="1" add="/movies" cancel="">
  <movie id="0" name="Rambo" date="2013-06-08" length="120" price="5.0" regiseur="Tim Burton" edit="/movies/0" delete="/movies/0">
    <discription>Hier steht eine Inhaltsangabe zum Film...</discription>
    <actors>
      <actor id="0"/>
    </actors>
    <genres>
      <genre id="0"/>
    </genres>
    <stocks>
      <stock id="1" format="dvd" lent="true" retour="2013-09-12"/>
      <stock id="2" format="dvd" lent="true" retour="2013-09-12"/>
    </stocks>
  </movie>
</movies>
